TrafficControl.v
module TrafficControl(
    input wire reset,
    input wire clk,
    output wire l1_green,
    output wire l1_yellow,
    output wire l1_red,
    output wire l2_green,
    output wire l2_yellow,
    output wire l2_red,
    output wire l3_green,
    output wire l3_yellow,
    output wire l3_red,
    output wire l4_green,
    output wire l4_yellow,
    output wire l4_red
);

reg [3:0] state;
reg [4:0] counter;

parameter L1_G = 4'b0000;
parameter L1_Y = 4'b0001;
parameter L1_R = 4'b0010;
parameter L2_G = 4'b0011;
parameter L2_Y = 4'b0100;
parameter L2_R = 4'b0101;
parameter L3_G = 4'b0110;
parameter L3_Y = 4'b0111;
parameter L3_R = 4'b1000;
parameter L4_G = 4'b1001;
parameter L4_Y = 4'b1010;
parameter L4_R = 4'b1011;

always @(posedge clk or posedge reset) begin
    if (reset) begin
        state <= L1_R;
        counter <= 0;
    end else begin
        case (state)
            L1_G:
                if (counter < 30) begin
                    state <= L1_G;
                    counter <= counter + 1;
                end else begin
                    state <= L1_Y;
                    counter <= 0;
                end
            L1_Y:
                if (counter < 5) begin
                    state <= L1_Y;
                    counter <= counter + 1;
                end else begin
                    state <= L1_R;
                    counter <= 0;
                end
            L1_R:
                if (counter < 5) begin
                    state <= L1_R;
                    counter <= counter + 1;
                end else begin
                    state <= L2_G;
                    counter <= 0;
                end
            L2_G:
                if (counter < 20) begin
                    state <= L2_G;
                    counter <= counter + 1;
                end else begin
                    state <= L2_Y;
                    counter <= 0;
                end
            L2_Y:
                if (counter < 5) begin
                    state <= L2_Y;
                    counter <= counter + 1;
                end else begin
                    state <= L2_R;
                    counter <= 0;
                end
            L2_R:
                if (counter < 5) begin
                    state <= L2_R;
                    counter <= counter + 1;
                end else begin
                    state <= L3_G;
                    counter <= 0;
                end
            L3_G:
                if (counter < 30) begin
                    state <= L3_G;
                    counter <= counter + 1;
                end else begin
                    state <= L3_Y;
                    counter <= 0;
                end
            L3_Y:
                if (counter < 5) begin
                    state <= L3_Y;
                    counter <= counter + 1;
                end else begin
                    state <= L3_R;
                    counter <= 0;
                end
            L3_R:
                if (counter < 5) begin
                    state <= L3_R;
                    counter <= counter + 1;
                end else begin
                    state <= L4_G;
                    counter <= 0;
                end
            L4_G:
                if (counter < 20) begin
                    state <= L4_G;
                    counter <= counter + 1;
                end else begin
                    state <= L4_Y;
                    counter <= 0;
                end
            L4_Y:
                if (counter < 5) begin
                    state <= L4_Y;
                    counter <= counter + 1;
                end else begin
                    state <= L4_R;
                    counter <= 0;
                end
            L4_R:
                if (counter < 5) begin
                    state <= L4_R;
                    counter <= counter + 1;
                end else begin
                    state <= L1_G;
                    counter <= 0;
                end
        endcase
    end
end

assign l1_green = (state == L1_G);
assign l1_yellow = (state == L1_Y);
assign l1_red = (state == L1_R);
assign l2_green = (state == L2_G);
assign l2_yellow = (state == L2_Y);
assign l2_red = (state == L2_R);
assign l3_green = (state == L3_G);
assign l3_yellow = (state == L3_Y);
assign l3_red = (state == L3_R);
assign l4_green = (state == L4_G);
assign l4_yellow = (state == L4_Y);
assign l4_red = (state == L4_R);

endmodule

module TrafficControlTestbench;

reg reset;
reg clk;
wire l1_green;
wire l1_yellow;
wire l1_red;
wire l2_green;
wire l2_yellow;
wire l2_red;
wire l3_green;
wire l3_yellow;
wire l3_red;
wire l4_green;
wire l4_yellow;
wire l4_red;

TrafficControl dut(
    .reset(reset),
    .clk(clk),
    .l1_green(l1_green),
    .l1_yellow(l1_yellow),
    .l1_red(l1_red),
    .l2_green(l2_green),
    .l2_yellow(l2_yellow),
    .l2_red(l2_red),
    .l3_green(l3_green),
    .l3_yellow(l3_yellow),
    .l3_red(l3_red),
    .l4_green(l4_green),
    .l4_yellow(l4_yellow),
    .l4_red(l4_red)
);

initial begin
  $dumpfile("dump.vcd");
  $dumpvars(0,dut);
    reset = 1;
    clk = 0;
    #10;
    reset = 0;
    #100;
    $finish;
end

always begin
    #5;
    clk = ~clk;
end

endmodule

dump.vcd
$date
	Wed Jun 07 18:16:44 2023
$end
$version
	Icarus Verilog
$end
$timescale
	1s
$end
$scope module TrafficControlTestbench $end
$scope module dut $end
$var wire 1 ! clk $end
$var wire 1 " reset $end
$var wire 1 # l4_yellow $end
$var wire 1 $ l4_red $end
$var wire 1 % l4_green $end
$var wire 1 & l3_yellow $end
$var wire 1 ' l3_red $end
$var wire 1 ( l3_green $end
$var wire 1 ) l2_yellow $end
$var wire 1 * l2_red $end
$var wire 1 + l2_green $end
$var wire 1 , l1_yellow $end
$var wire 1 - l1_red $end
$var wire 1 . l1_green $end
$var parameter 4 / L1_G $end
$var parameter 4 0 L1_R $end
$var parameter 4 1 L1_Y $end
$var parameter 4 2 L2_G $end
$var parameter 4 3 L2_R $end
$var parameter 4 4 L2_Y $end
$var parameter 4 5 L3_G $end
$var parameter 4 6 L3_R $end
$var parameter 4 7 L3_Y $end
$var parameter 4 8 L4_G $end
$var parameter 4 9 L4_R $end
$var parameter 4 : L4_Y $end
$var reg 5 ; counter [4:0] $end
$var reg 4 < state [3:0] $end
$upscope $end
$upscope $end
$enddefinitions $end
$comment Show the parameter values. $end
$dumpall
b1010 :
b1011 9
b1001 8
b111 7
b1000 6
b110 5
b100 4
b101 3
b11 2
b1 1
b10 0
b0 /
$end
#0
$dumpvars
b10 <
b0 ;
0.
1-
0,
0+
0*
0)
0(
0'
0&
0%
0$
0#
1"
0!
$end
#5
1!
#10
0!
0"
#15
b1 ;
1!
#20
0!
#25
b10 ;
1!
#30
0!
#35
b11 ;
1!
#40
0!
#45
b100 ;
1!
#50
0!
#55
b101 ;
1!
#60
0!
#65
b0 ;
0-
1+
b11 <
1!
#70
0!
#75
b1 ;
1!
#80
0!
#85
b10 ;
1!
#90
0!
#95
b11 ;
1!
#100
0!
#105
b100 ;
1!
